alu_4_bit.v
module alu_4_bit (A,B,op,out_alu);
input [3:0] A,B;
input [2:0] op;
output reg [3:0] out_alu;

always @(*)
    begin
      casex(op)

      
      3'b000 :out_alu= A+B;//addition
      3'b001 :out_alu= A-B;//subtraction
      3'b010 :out_alu= A&B;//logical AND
      3'b011 :out_alu= A|B;//logical OR
      3'b100 :out_alu= ~A;//logical NOT
      3'b101 :out_alu= A<<1;//left shift
      3'b110 :out_alu=A>>1;//right shift
      3'b111 :out_alu=A^B;//xor operation
      default:out_alu=0;
      endcase

    end
endmodule

alu_4_bit_tb.v
`timescale 1ns/1ps
module alu_4_bit_tb;
reg [3:0] A_tb,B_tb;
reg [2:0] op_tb;
wire [3:0] out_alu_tb;


alu_4_bit dut(A_tb,B_tb,op_tb,out_alu_tb);

initial
begin
$dumpfile("aluwaveform.vcd");
$dumpvars(0,alu_4_bit_tb);
end

initial 
begin

op_tb=3'b000; A_tb=4'b0011;B_tb=4'b0001;
#10
op_tb=3'b001; A_tb=4'b0011;B_tb=4'b0001;
#10
op_tb=3'b010; A_tb=4'b0011;B_tb=4'b0001;
#10
op_tb=3'b011; A_tb=4'b0011;B_tb=4'b0001;
#10
op_tb=3'b100; A_tb=4'b0011;B_tb=4'b0001;
#10
op_tb=3'b101; A_tb=4'b0011;B_tb=4'b0001;
#10
op_tb=3'b110; A_tb=4'b0011;B_tb=4'b0001;
#10
op_tb=3'b111; A_tb=4'b0011;B_tb=4'b0001;
end

initial
begin

$monitor("....op=%b........,......A=%b.......,.......B=%b.......,....out=%b... ",op_tb,A_tb,B_tb,out_alu_tb);
end
endmodule

aluwaveform.vcd
$date
	Wed Jul 29 15:55:19 2026
$end
$version
	Icarus Verilog
$end
$timescale
	1ps
$end
$scope module alu_4_bit_tb $end
$var wire 4 ! out_alu_tb [3:0] $end
$var reg 4 " A_tb [3:0] $end
$var reg 4 # B_tb [3:0] $end
$var reg 3 $ op_tb [2:0] $end
$scope module dut $end
$var wire 4 % A [3:0] $end
$var wire 4 & B [3:0] $end
$var wire 3 ' op [2:0] $end
$var reg 4 ( out_alu [3:0] $end
$upscope $end
$upscope $end
$enddefinitions $end
#0
$dumpvars
b100 (
b0 '
b1 &
b11 %
b0 $
b1 #
b11 "
b100 !
$end
#10000
b10 !
b10 (
b1 $
b1 '
#20000
b1 !
b1 (
b10 $
b10 '
#30000
b11 !
b11 (
b11 $
b11 '
#40000
b1100 !
b1100 (
b100 $
b100 '
#50000
b110 !
b110 (
b101 $
b101 '
#60000
b1 !
b1 (
b110 $
b110 '
#70000
b10 !
b10 (
b111 $
b111 '
